flashbake/__init__.py
flashbake/commit.py
flashbake/compat.py
flashbake/console.py
flashbake/context.py
flashbake/control.py
flashbake/git.py
flashbake/plugins/__init__.py
flashbake/plugins/default.py
flashbake/plugins/feed.py
flashbake/plugins/itunes.py
flashbake/plugins/lastfm.py
flashbake/plugins/location.py
flashbake/plugins/mail.py
flashbake/plugins/music.py
flashbake/plugins/timestamp.py
flashbake/plugins/timezone.py
flashbake/plugins/twitter.py
flashbake/plugins/uptime.py
flashbake/plugins/weather.py
flashbake-0.30.0.dist-info/COPYING.txt
flashbake-0.30.0.dist-info/METADATA
flashbake-0.30.0.dist-info/WHEEL
flashbake-0.30.0.dist-info/entry_points.txt
flashbake-0.30.0.dist-info/top_level.txt
flashbake-0.30.0.dist-info/RECORD
