Metadata-Version: 2.1
Name: flashbake
Version: 0.30.0
Summary: Automation to feed lifelog data into a version control message stream.
Home-page: http://thecommandline.net
Author: Thomas Gideon
Author-email: cmdln@thecommandline.net
Maintainer: Thomas Gideon
Maintainer-email: cmdln@thecommandline.net
License: GPLv3
Download-URL: https://github.com/commandline/flashbake/downloads
Platform: noarch
Classifier: Development Status :: 4 - Beta
Classifier: Environment :: Console
Classifier: Intended Audience :: End Users/Desktop
Classifier: License :: OSI Approved :: GNU General Public License (GPL)
Classifier: Operating System :: MacOS :: MacOS X
Classifier: Operating System :: POSIX :: Linux
Classifier: Programming Language :: Python
Classifier: Topic :: Artistic Software
License-File: COPYING.txt
Requires-Dist: enum34 (>=1.0.3)
Requires-Dist: feedparser (>=4.1)
Requires-Dist: requests (>=2.23.0)
